pdm_utils/__init__.py
pdm_utils/__main__.py
pdm_utils/run.py
pdm_utils/classes/__init__.py
pdm_utils/classes/alchemyhandler.py
pdm_utils/classes/aragornhandler.py
pdm_utils/classes/bundle.py
pdm_utils/classes/cds.py
pdm_utils/classes/cdspair.py
pdm_utils/classes/dbcomparesummary.py
pdm_utils/classes/error.py
pdm_utils/classes/evaluation.py
pdm_utils/classes/fileio.py
pdm_utils/classes/filter.py
pdm_utils/classes/genome.py
pdm_utils/classes/genomepair.py
pdm_utils/classes/genometriad.py
pdm_utils/classes/progress.py
pdm_utils/classes/randomfieldupdatehandler.py
pdm_utils/classes/source.py
pdm_utils/classes/ticket.py
pdm_utils/classes/tmrna.py
pdm_utils/classes/trna.py
pdm_utils/classes/trnascansehandler.py
pdm_utils/constants/__init__.py
pdm_utils/constants/constants.py
pdm_utils/constants/db_schema_0.py
pdm_utils/constants/eval_descriptions.py
pdm_utils/constants/schema_conversions.py
pdm_utils/functions/__init__.py
pdm_utils/functions/annotation.py
pdm_utils/functions/basic.py
pdm_utils/functions/cartography.py
pdm_utils/functions/configfile.py
pdm_utils/functions/deeptmhmm.py
pdm_utils/functions/eval_modes.py
pdm_utils/functions/fasta.py
pdm_utils/functions/fileio.py
pdm_utils/functions/flat_files.py
pdm_utils/functions/multiprocess.py
pdm_utils/functions/multithread.py
pdm_utils/functions/mysqldb.py
pdm_utils/functions/mysqldb_basic.py
pdm_utils/functions/ncbi.py
pdm_utils/functions/parsing.py
pdm_utils/functions/phagesdb.py
pdm_utils/functions/pham_alignment.py
pdm_utils/functions/phameration.py
pdm_utils/functions/pipeline_shells.py
pdm_utils/functions/pipelines_basic.py
pdm_utils/functions/querying.py
pdm_utils/functions/rpsblast.py
pdm_utils/functions/server.py
pdm_utils/functions/subprocess.py
pdm_utils/functions/tickets.py
pdm_utils/functions/url_basic.py
pdm_utils/pipelines/__init__.py
pdm_utils/pipelines/cluster_db.py
pdm_utils/pipelines/compare_db.py
pdm_utils/pipelines/convert_db.py
pdm_utils/pipelines/export_db.py
pdm_utils/pipelines/find_domains.py
pdm_utils-1.1.3.dist-info/LICENSE
pdm_utils-1.1.3.dist-info/METADATA
pdm_utils-1.1.3.dist-info/WHEEL
pdm_utils-1.1.3.dist-info/entry_points.txt
pdm_utils-1.1.3.dist-info/top_level.txt
pdm_utils-1.1.3.dist-info/RECORD
