Metadata-Version: 2.1
Name: pdm-utils
Version: 1.1.3
Summary: MySQL phage genomics database management utilities
Home-page: https://github.com/SEA-PHAGES/pdm_utils
Author: Christian Gauthier
Author-email: chg60@pitt.edu
Project-URL: Documentation, https://pdm-utils.readthedocs.io/en/latest/
Project-URL: Source, https://github.com/SEA-PHAGES/pdm_utils/
Classifier: Intended Audience :: Science/Research
Classifier: License :: OSI Approved :: GNU General Public License v3 (GPLv3)
Classifier: Operating System :: MacOS
Classifier: Operating System :: POSIX :: Linux
Classifier: Programming Language :: Python
Classifier: Programming Language :: Python :: 3
Classifier: Programming Language :: Python :: 3 :: Only
Classifier: Programming Language :: Python :: 3.7
Classifier: Programming Language :: Python :: 3.8
Classifier: Programming Language :: Python :: 3.9
Requires-Python: >=3.7
License-File: LICENSE
Requires-Dist: biopython (==1.77)
Requires-Dist: kaleido (==0.2.1)
Requires-Dist: networkx (>=3.0)
Requires-Dist: pandas (==2.0.2)
Requires-Dist: paramiko (>=2.7.2)
Requires-Dist: parasail (==1.3.4)
Requires-Dist: phamclust (>=1.0.1)
Requires-Dist: phammseqs (>=1.0.4)
Requires-Dist: psutil (==5.9.5)
Requires-Dist: pybiolib (>=1.1.918)
Requires-Dist: pymysql (==0.9.3)
Requires-Dist: pyyaml (>=5.3.1)
Requires-Dist: scikit-learn (==1.2.2)
Requires-Dist: sqlalchemy (==1.4.2)
Requires-Dist: tabulate (>=0.8.3)
Requires-Dist: urllib3 (==1.26.0)
